tl/__init__.py
tl/tl.py
clintl-1.2.1.dist-info/COPYING
clintl-1.2.1.dist-info/METADATA
clintl-1.2.1.dist-info/WHEEL
clintl-1.2.1.dist-info/entry_points.txt
clintl-1.2.1.dist-info/top_level.txt
clintl-1.2.1.dist-info/RECORD
