Metadata-Version: 2.1
Name: clintl
Version: 1.2.1
Summary: Timeline figures from json or yaml-formatted input
Author: Rainer Strotmann
Author-email: rainer.strotmann@mailbox.org
License: GPL-3.0-or-later
Platform: UNKNOWN
Classifier: Programming Language :: Python :: 3
Classifier: Operating System :: OS Independent
Classifier: License :: OSI Approved :: GNU General Public License v3 or later (GPLv3+)
Requires-Python: >=3.7
License-File: COPYING
Requires-Dist: typer
Requires-Dist: pycairo
Requires-Dist: python-dateutil
Requires-Dist: DateTime
